{"cameraMode":{"drawMode":0,"name":"Shaded","section":"Shading Mode"},"sceneLighting":true,"audioPlay":false,"sceneViewState":{"m_AlwaysRefresh":false,"showFog":true,"showSkybox":true,"showFlares":true,"showImageEffects":true,"showParticleSystems":true,"showVisualEffectGraphs":true,"m_FxEnabled":true},"in2DMode":false,"pivot":{"x":-4390.13037109375,"y":-995.6268310546875,"z":-569.36376953125},"rotation":{"x":-0.08212493360042572,"y":0.7597708106040955,"z":-0.09786415845155716,"w":-0.6374819874763489},"size":3232.179443359375,"orthographic":false}